mrpeace
tests
